{"dependencies":[],"generated":{"js":"var global = (1,eval)(\"this\");\nvar t=(0,eval)(\"this\"),e=\"Expected a function\",n=NaN,r=\"[object Symbol]\",i=/^\\s+|\\s+$/g,o=/^[-+]0x[0-9a-f]+$/i,u=/^0b[01]+$/i,f=/^0o[0-7]+$/i,c=parseInt,a=\"object\"==typeof t&&t&&t.Object===Object&&t,s=\"object\"==typeof self&&self&&self.Object===Object&&self,v=a||s||Function(\"return this\")(),l=Object.prototype,p=l.toString,b=Math.max,y=Math.min,m=function(){return v.Date.now()};function d(t,n,r){var i,o,u,f,c,a,s=0,v=!1,l=!1,p=!0;if(\"function\"!=typeof t)throw new TypeError(e);function d(e){var n=i,r=o;return i=o=void 0,s=e,f=t.apply(r,n)}function h(t){var e=t-a;return void 0===a||e>=n||e<0||l&&t-s>=u}function O(){var t=m();if(h(t))return x(t);c=setTimeout(O,function(t){var e=n-(t-a);return l?y(e,u-(t-s)):e}(t))}function x(t){return c=void 0,p&&i?d(t):(i=o=void 0,f)}function T(){var t=m(),e=h(t);if(i=arguments,o=this,a=t,e){if(void 0===c)return function(t){return s=t,c=setTimeout(O,n),v?d(t):f}(a);if(l)return c=setTimeout(O,n),d(a)}return void 0===c&&(c=setTimeout(O,n)),f}return n=g(n)||0,j(r)&&(v=!!r.leading,u=(l=\"maxWait\"in r)?b(g(r.maxWait)||0,n):u,p=\"trailing\"in r?!!r.trailing:p),T.cancel=function(){void 0!==c&&clearTimeout(c),s=0,i=a=o=c=void 0},T.flush=function(){return void 0===c?f:x(m())},T}function j(t){var e=typeof t;return!!t&&(\"object\"==e||\"function\"==e)}function h(t){return!!t&&\"object\"==typeof t}function O(t){return\"symbol\"==typeof t||h(t)&&p.call(t)==r}function g(t){if(\"number\"==typeof t)return t;if(O(t))return n;if(j(t)){var e=\"function\"==typeof t.valueOf?t.valueOf():t;t=j(e)?e+\"\":e}if(\"string\"!=typeof t)return 0===t?t:+t;t=t.replace(i,\"\");var r=u.test(t);return r||f.test(t)?c(t.slice(2),r?2:8):o.test(t)?n:+t}module.exports=d;"},"hash":"1abcca04ba5a3f4a0ad9b175ca8444d8","cacheData":{"env":{}}}